LICENSE
MANIFEST.in
README.md
VERSION
setup.py
bin/stacklift
stacklift/cfn_deploy.py
stacklift/cli.py
stacklift/deploy_group.py
stacklift/deploy_template.py
stacklift/extract_archive.py
stacklift/global_config.py
stacklift/read_config.py
stacklift/templates_config.py
stacklift/upload_archive.py
stacklift/validate_configs.py
stacklift.egg-info/PKG-INFO
stacklift.egg-info/SOURCES.txt
stacklift.egg-info/dependency_links.txt
stacklift.egg-info/requires.txt
stacklift.egg-info/top_level.txt