Metadata-Version: 2.1
Name: stacklift
Version: 0.0.13
Summary: CloudFormation stack management tool
Home-page: https://github.com/syginc/stacklift
Author: syginc
License: MIT
Keywords: aws cloudformation
Platform: UNKNOWN
Classifier: Programming Language :: Python :: 3.6
Classifier: Topic :: Software Development :: Build Tools
Requires-Python: >=3.6
License-File: LICENSE
